cms_plots/__init__.py
cms_plots/_version.py
cms_plots/dictionary.py
cms_plots/electronic.py
cms_plots/plotting.py
cms_plots/templates/band_structure.graph_template
cms_plots/templates/band_structure.html_template
cms_plots/templates/line.graph_template
cms_plots/templates/line.html_template
cms_plots-2025.5.7.dist-info/licenses/AUTHORS.rst
cms_plots-2025.5.7.dist-info/licenses/LICENSE
cms_plots-2025.5.7.dist-info/METADATA
cms_plots-2025.5.7.dist-info/WHEEL
cms_plots-2025.5.7.dist-info/top_level.txt
cms_plots-2025.5.7.dist-info/zip-safe
cms_plots-2025.5.7.dist-info/RECORD
